{
  "Base": {
    "BaseDir": ".",
    "LogPath": "./Log/",
    "NetworkId": 1567651915,
    "ChainId": "0",
    "BlockTime": 5,
    "PublicIP": "127.116.237.14",
    "PortBase": 10000,
    "LogLevel": 1,
    "LocalRpcPortOffset": 138,
    "EnableLocalRpc": true,
    "JsonRpcPortOffset": 136,
    "EnableJsonRpc": true,
    "HttpRestPortOffset": 135,
    "HttpCertPath": "",
    "HttpKeyPath": "",
    "RestEnable": true,
    "ChannelProtocol": "tcp",
    "ChannelPortOffset": 302,
    "ChannelClientType": "rpc",
    "ChannelRevealTimeout": "20",
    "ChannelSettleTimeout": "50",
    "BlockDelay": "",
    "DBPath": "./DB",
    "PpListenAddr": "",
    "PpBootstrap": null,
    "ChainRestAddrs": [
      "http://52.163.217.230:10334",
      "http://52.163.217.230:20334",
      "http://139.219.141.206:20334"
    ],
    "ChainRpcAddrs": [
      "http://52.163.217.230:10336",
      "http://52.163.217.230:20336",
      "http://139.219.141.206:20336"
    ],
    "NATProxyServerAddrs": "",
    "DspProtocol": "tcp",
    "DspPortOffset": 301,
    "AutoSetupDNSEnable": false,
    "TrackerPortOffset": 137,
    "TrackerProtocol": "tcp",
    "DnsNodeMaxNum": 100,
    "SeedInterval": 600,
    "DnsChannelDeposit": 1000000000,
    "Trackers": [],
    "DNSWalletAddrs": [
      "AcJdio7iRMzPxCWgBjSLSqKZcXMjNRtLpd"
    ],
    "WalletDir": "./wallet.dat"
  },
  "Fs": {
    "FsRepoRoot": "./FS",
    "FsFileRoot": "./Downloads",
    "FsType": 1,
    "EnableBackup": true,
    "FsGCPeriod": "1h"
  },
  "Bootstraps": []
}